myqlm_contrib-1.10.1.dist-info/licenses/LICENSE
qat/plugins/hook_sabre.py
qat/sabre/__init__.py
qat/sabre/sabre.py
myqlm_contrib-1.10.1.dist-info/METADATA
myqlm_contrib-1.10.1.dist-info/WHEEL
myqlm_contrib-1.10.1.dist-info/top_level.txt
myqlm_contrib-1.10.1.dist-info/RECORD
