Metadata-Version: 2.4
Name: myqlm-contrib
Version: 1.10.1
Summary: Modules developed by the myQLM community
Home-page: https://atos.net/en/lp/myqlm
Author: Atos Quantum Lab
Author-email: myqlm@atos.net
License: Atos myQLM EULA
Project-URL: Documentation, https://myqlm.github.io
Project-URL: Source Code, https://github.com/myQLM/myqlm-contrib
License-File: LICENSE
Requires-Dist: qat-core
Requires-Dist: qat-comm
Requires-Dist: networkx
Dynamic: author
Dynamic: author-email
Dynamic: description
Dynamic: description-content-type
Dynamic: home-page
Dynamic: license
Dynamic: license-file
Dynamic: project-url
Dynamic: requires-dist
Dynamic: summary
